aehmc/__init__.py
aehmc/_version.py
aehmc/algorithms.py
aehmc/hmc.py
aehmc/integrators.py
aehmc/mass_matrix.py
aehmc/metrics.py
aehmc/nuts.py
aehmc/proposals.py
aehmc/step_size.py
aehmc/termination.py
aehmc/trajectory.py
aehmc/utils.py
aehmc/window_adaptation.py
aehmc_nightly-0.0.10.dist-info/LICENSE
aehmc_nightly-0.0.10.dist-info/METADATA
aehmc_nightly-0.0.10.dist-info/WHEEL
aehmc_nightly-0.0.10.dist-info/top_level.txt
aehmc_nightly-0.0.10.dist-info/RECORD
