Metadata-Version: 2.1
Name: aehmc-nightly
Version: 0.0.10
Summary: HMC samplers in Aesara
Home-page: http://github.com/aesara-devs/aehmc
Maintainer: Aesara Developers
Maintainer-email: aesara.devs@gmail.com
Classifier: Development Status :: 4 - Beta
Classifier: Intended Audience :: Science/Research
Classifier: Intended Audience :: Developers
Classifier: License :: OSI Approved :: MIT License
Classifier: Operating System :: OS Independent
Classifier: Programming Language :: Python
Classifier: Programming Language :: Python :: 3
Classifier: Programming Language :: Python :: 3.7
Classifier: Programming Language :: Python :: 3.8
Classifier: Programming Language :: Python :: 3.9
Classifier: Programming Language :: Python :: Implementation :: CPython
Classifier: Programming Language :: Python :: Implementation :: PyPy
Requires-Python: >=3.7
License-File: LICENSE
Requires-Dist: numpy (>=1.18.1)
Requires-Dist: scipy (>=1.4.0)
Requires-Dist: aesara (>=2.8.3)
Requires-Dist: aeppl (>=0.0.38)
